slack_react.py
slack_react-0.3.3.dist-info/LICENSE
slack_react-0.3.3.dist-info/METADATA
slack_react-0.3.3.dist-info/WHEEL
slack_react-0.3.3.dist-info/entry_points.txt
slack_react-0.3.3.dist-info/top_level.txt
slack_react-0.3.3.dist-info/RECORD
