Metadata-Version: 2.1
Name: slack-react
Version: 0.3.3
Summary: Add reactions that spell out messages to Slack messages
Author-email: Philipp Schmitt <philipp@schmitt.co>
License: GNU GENERAL PUBLIC LICENSE
Keywords: slack,reactions
Classifier: Programming Language :: Python :: 3
Requires-Python: >=3.9
License-File: LICENSE
Requires-Dist: appdirs
Requires-Dist: rich
Requires-Dist: slack-sdk
